pysem_strings/__init__.py
pysem_strings/strings.py
pysem_strings-0.1.dist-info/LICENSE
pysem_strings-0.1.dist-info/METADATA
pysem_strings-0.1.dist-info/WHEEL
pysem_strings-0.1.dist-info/top_level.txt
pysem_strings-0.1.dist-info/RECORD
