Metadata-Version: 2.1
Name: pysem-strings
Version: 0.1
Summary: UNKNOWN
Home-page: https://github.com/pysem/strings
Author: Adrián Toral
Author-email: adriantoral@sertor.es
License: UNKNOWN
Project-URL: Website, https://github.com/pysem/strings
Project-URL: Issues, https://github.com/pysem/strings/issues
Keywords: python,strings,utilities,python-strings,python-strings-utilities
Platform: UNKNOWN
Classifier: Programming Language :: Python :: 3
Classifier: License :: OSI Approved :: GNU General Public License v3 (GPLv3)
Classifier: Operating System :: OS Independent
Classifier: Topic :: Software Development :: Libraries :: Python Modules
Requires-Python: >=3.8
License-File: LICENSE
